bacy-1.3.2.dist-info/METADATA
bacy-1.3.2.dist-info/WHEEL
bacy.libs/libgcc_s-b5472b99.so.1
bacy/__init__.py
bacy/bacy.cpython-312-i386-linux-musl.so
bacy-1.3.2.dist-info/RECORD
